solomonai_backend_client_sdk/__init__.py
solomonai_backend_client_sdk/api_client.py
solomonai_backend_client_sdk/api_response.py
solomonai_backend_client_sdk/configuration.py
solomonai_backend_client_sdk/exceptions.py
solomonai_backend_client_sdk/rest.py
solomonai_backend_client_sdk/api/__init__.py
solomonai_backend_client_sdk/api/accounting_service_api.py
solomonai_backend_client_sdk/api/financial_service_api.py
solomonai_backend_client_sdk/api/social_service_api.py
solomonai_backend_client_sdk/api/user_service_v2_api.py
solomonai_backend_client_sdk/api/workspace_service_api.py
solomonai_backend_client_sdk/api/workspace_service_rest_api.py
solomonai_backend_client_sdk/models/__init__.py
solomonai_backend_client_sdk/models/accept_follow_profile_response.py
solomonai_backend_client_sdk/models/accept_team_member_invitation_body.py
solomonai_backend_client_sdk/models/accept_team_member_invitation_response.py
solomonai_backend_client_sdk/models/account.py
solomonai_backend_client_sdk/models/account_balance_history.py
solomonai_backend_client_sdk/models/account_statements.py
solomonai_backend_client_sdk/models/account_status.py
solomonai_backend_client_sdk/models/account_type.py
solomonai_backend_client_sdk/models/accounting_attachment.py
solomonai_backend_client_sdk/models/accounting_integration_merge_link.py
solomonai_backend_client_sdk/models/actionable_insight.py
solomonai_backend_client_sdk/models/actor.py
solomonai_backend_client_sdk/models/actor_type.py
solomonai_backend_client_sdk/models/add_comment_quality_score_response.py
solomonai_backend_client_sdk/models/add_default_pockets_to_bank_account_request.py
solomonai_backend_client_sdk/models/add_default_pockets_to_bank_account_response.py
solomonai_backend_client_sdk/models/add_note_to_financial_user_profile_request.py
solomonai_backend_client_sdk/models/add_note_to_financial_user_profile_response.py
solomonai_backend_client_sdk/models/add_note_to_recurring_transaction_request.py
solomonai_backend_client_sdk-1.64.4.dist-info/METADATA
solomonai_backend_client_sdk-1.64.4.dist-info/WHEEL
solomonai_backend_client_sdk-1.64.4.dist-info/top_level.txt
solomonai_backend_client_sdk-1.64.4.dist-info/RECORD
