Metadata-Version: 2.4
Name: solomonai-backend-client-sdk
Version: 1.64.4
Summary: Solomonai Backend Client SDK
Home-page: 
Author: Solomonai Engineering
Author-email: yoanyomba@solomonai.co
License: Apache 2.0 License
Keywords: OpenAPI,OpenAPI-Generator,Solomonai Backend Client SDK
Requires-Dist: urllib3<2.1.0,>=1.25.3
Requires-Dist: python-dateutil
Requires-Dist: pydantic>=2
Requires-Dist: typing-extensions>=4.7.1
Dynamic: author
Dynamic: author-email
Dynamic: description
Dynamic: description-content-type
Dynamic: keywords
Dynamic: license
Dynamic: requires-dist
Dynamic: summary
